phenix/__init__.py
phenix/bibtex.py
phenix/constants.py
phenix/phenix.png
phenix/protocols.conf
phenix/wizards.py
phenix/protocols/__init__.py
phenix/protocols/protocol_dock_and_rebuild_alphafold_model.py
phenix/protocols/protocol_dock_in_map.py
phenix/protocols/protocol_dock_predicted_alphafold2_model.py
phenix/protocols/protocol_emringer.py
phenix/protocols/protocol_molprobity.py
phenix/protocols/protocol_process_predicted_alphafold2_model.py
phenix/protocols/protocol_real_space_refine.py
phenix/protocols/protocol_rebuild_docked_predicted_alphafold2_model.py
phenix/protocols/protocol_refinement_base.py
phenix/protocols/protocol_search_fit.py
phenix/protocols/protocol_superpose_pdbs.py
phenix/protocols/protocol_validation_cryoem.py
phenix/tests/__init__.py
phenix/tests/test_phenix.py
phenix/tests/test_phenix_alphafold.py
phenix/tests/test_phenix_pdb_cif.py
phenix/tests/test_protocol_dock_in_map.py
phenix/tests/test_protocol_emringer.py
phenix/tests/test_protocol_molprobity.py
phenix/tests/test_protocol_real_space_refine.py
phenix/tests/test_protocol_search_fit.py
phenix/tests/test_protocol_superpose_pdbs.py
phenix/tests/test_protocol_validation_cryoem.py
phenix/viewers/__init__.py
phenix/viewers/viewer_dock_in_map.py
phenix/viewers/viewer_emringer.py
phenix/viewers/viewer_molprobity.py
phenix/viewers/viewer_process_predicted_alphafold.py
phenix/viewers/viewer_real_space_refine.py
phenix/viewers/viewer_refinement_base.py
phenix/viewers/viewer_search_fit.py
phenix/viewers/viewer_superpose_pdbs.py
phenix/viewers/viewer_validation_cryoem.py
scipion_em_phenix-3.2.1.dist-info/LICENSE
scipion_em_phenix-3.2.1.dist-info/METADATA
scipion_em_phenix-3.2.1.dist-info/WHEEL
scipion_em_phenix-3.2.1.dist-info/entry_points.txt
scipion_em_phenix-3.2.1.dist-info/top_level.txt
scipion_em_phenix-3.2.1.dist-info/RECORD
