Metadata-Version: 2.1
Name: scipion-em-phenix
Version: 3.2.1
Summary: PHENIX programs in Scipion. Warning: Install PHENIX v. 1-17
Home-page: https://github.com/scipion-em/scipion-em-phenix
Author: Roberto Marabini, Marta Martinez
Author-email: scipion@cnb.csic.es
License: UNKNOWN
Keywords: scipion cryoem imageprocessing scipion-3.0
Platform: UNKNOWN
Classifier: Programming Language :: Python :: 3
Requires-Dist: scipion-em-ccp4 (>=3.0.0)
Requires-Dist: mpi4py (>=3.0.3)
